aioconductor/__init__.py
aioconductor/component.py
aioconductor/conductor.py
aioconductor/config.py
aioconductor/exc.py
aioconductor/logging.py
aioconductor/naming.py
aioconductor/py.typed
AIOConductor-0.2.dist-info/LICENCE.rst
AIOConductor-0.2.dist-info/METADATA
AIOConductor-0.2.dist-info/WHEEL
AIOConductor-0.2.dist-info/top_level.txt
AIOConductor-0.2.dist-info/RECORD
