Metadata-Version: 2.1
Name: AIOConductor
Version: 0.2
Summary: asynchronous application orchestrator
Home-page: https://github.com/Cottonwood-Technology/AIOConductor
Author: Cottonwood Technology
Author-email: info@cottonwood.tech
License: BSD
Keywords: asyncio asynchronous orchestration orchestrator conductor injector service component
Platform: UNKNOWN
Classifier: Intended Audience :: Developers
Classifier: License :: OSI Approved :: BSD License
Classifier: Programming Language :: Python
Classifier: Programming Language :: Python :: 3.6
Classifier: Programming Language :: Python :: 3.7
Classifier: Programming Language :: Python :: 3.8
Classifier: Programming Language :: Python :: 3.9
Classifier: Programming Language :: Python :: Implementation :: CPython
Classifier: Framework :: AsyncIO
